{
  "name": "lane_restrictions",
  "fetched_at": "2026-05-18T17:03:29.169Z",
  "source_url": "https://www.511pa.com/list/events/traffic?start=0&length=250&order%5Bi%5D=8&order%5Bdir%5D=desc",
  "count": 3,
  "items": [
    {
      "id": "258600",
      "eventId": "258600",
      "type": "Incident - Major Route",
      "roadway": "I-70",
      "state": "Pennsylvania",
      "county": "Washington",
      "route": "I-70",
      "direction": "EAST",
      "description": "Crash on I-70 eastbound between Exit 1: WEST ALEXANDER and Exit 6: PA 231 - CLAYSVILLE. There is a lane restriction.",
      "start_time": "5/18/26, 12:51 PM",
      "anticipated_end_time": "5/18/26, 2:30 PM",
      "last_updated": "5/18/26, 12:54 PM",
      "formatted": "I-70 (Washington County) | Crash on I-70 eastbound between Exit 1: WEST ALEXANDER and Exit 6: PA 231 - CLAYSVILLE. Estimated Reopen: 5/18/26 - 14:30"
    },
    {
      "id": "258591",
      "eventId": "258591",
      "type": "Incident - Major Route",
      "roadway": "I-79",
      "state": "Pennsylvania",
      "county": "Allegheny",
      "route": "I-79",
      "direction": "SOUTH",
      "description": "Disabled vehicle on I-79 southbound at Exit 54: PA 50 - BRIDGEVILLE. There is a lane restriction.",
      "start_time": "5/18/26, 12:30 PM",
      "anticipated_end_time": "5/18/26, 2:00 PM",
      "last_updated": "5/18/26, 12:33 PM",
      "formatted": "I-79 (Allegheny County) | Disabled vehicle on I-79 southbound at Exit 54: PA 50 - BRIDGEVILLE. Estimated Reopen: 5/18/26 - 14:00"
    },
    {
      "id": "258586",
      "eventId": "258586",
      "type": "Incident - Major Route",
      "roadway": "I-81",
      "state": "Pennsylvania",
      "county": "Cumberland",
      "route": "I-81",
      "direction": "NORTH",
      "description": "Crash on I-81 northbound 3.7 miles south of Exit 37: PA 233 - NEWVILLE. There is a lane restriction.",
      "start_time": "5/18/26, 12:24 PM",
      "anticipated_end_time": "5/18/26, 2:30 PM",
      "last_updated": "5/18/26, 12:26 PM",
      "formatted": "I-81 (Cumberland County) | Crash on I-81 northbound 3.7 miles south of Exit 37: PA 233 - NEWVILLE. Estimated Reopen: 5/18/26 - 14:30"
    }
  ]
}