{
  "name": "lane_restrictions",
  "fetched_at": "2026-04-10T14:43:04.046Z",
  "source_url": "https://www.511pa.com/list/events/traffic?start=0&length=250&order%5Bi%5D=8&order%5Bdir%5D=desc",
  "count": 3,
  "items": [
    {
      "type": "Incident - Major Route",
      "roadway": "I-83",
      "state": "Pennsylvania",
      "county": "York",
      "route": "I-83",
      "direction": "NORTH",
      "description": "Multi vehicle crash on I-83 northbound 0 miles NORTH of Exit 18: PA 124 - MT ROSE AVENUE. There is a lane restriction.",
      "start_time": "4/10/26, 10:30 AM",
      "anticipated_end_time": "4/10/26, 11:55 AM",
      "last_updated": "4/10/26, 10:35 AM",
      "formatted": "I-83 (York County) | Multi vehicle crash on I-83 northbound 0 miles NORTH of Exit 18: PA 124 - MT ROSE AVENUE. Estimated Reopen: 4/10/26 - 11:55"
    },
    {
      "type": "Incident - Major Route",
      "roadway": "I-95",
      "state": "Pennsylvania",
      "county": "Philadelphia",
      "route": "I-95",
      "direction": "NORTH",
      "description": "Multi vehicle crash on I-95 northbound between Exit 26: BETSY ROSS BR - NEW JERSEY and Exit 30: COTTMAN AVE/RHAWN ST. There is a lane restriction.",
      "start_time": "4/10/26, 10:16 AM",
      "anticipated_end_time": "4/10/26, 11:02 AM",
      "last_updated": "4/10/26, 10:31 AM",
      "formatted": "I-95 (Philadelphia County) | Multi vehicle crash on I-95 northbound between Exit 26: BETSY ROSS BR - NEW JERSEY and Exit 30: COTTMAN AVE/RHAWN ST. Estimated Reopen: 4/10/26 - 11:02"
    },
    {
      "type": "Incident - Major Route",
      "roadway": "US-11",
      "state": "Pennsylvania",
      "county": "Snyder",
      "route": "US-11",
      "direction": "SOUTH",
      "description": "Multi vehicle crash on US 11 southbound at EIGHTH AV. There is a lane restriction.",
      "start_time": "4/10/26, 9:48 AM",
      "anticipated_end_time": "4/10/26, 11:30 AM",
      "last_updated": "4/10/26, 10:08 AM",
      "formatted": "US-11 (Snyder County) | Multi vehicle crash on US 11 southbound at EIGHTH AV. Estimated Reopen: 4/10/26 - 11:30"
    }
  ]
}