{
  "name": "lane_restrictions",
  "fetched_at": "2026-04-10T10:51:48.133Z",
  "source_url": "https://www.511pa.com/list/events/traffic?start=0&length=250&order%5Bi%5D=8&order%5Bdir%5D=desc",
  "count": 2,
  "items": [
    {
      "type": "Incident - Major Route",
      "roadway": "US-30",
      "state": "Pennsylvania",
      "county": "Chester",
      "route": "US-30",
      "direction": "EAST",
      "description": "Multi vehicle crash on US 30 eastbound between Exit: US 322 - MANOR AVE and Exit: PA 113 SOUTH - DOWNINGTOWN. There is a lane restriction.",
      "start_time": "4/10/26, 6:40 AM",
      "anticipated_end_time": "4/10/26, 7:39 AM",
      "last_updated": "4/10/26, 6:42 AM",
      "formatted": "US-30 (Chester County) | Multi vehicle crash on US 30 eastbound between Exit: US 322 - MANOR AVE and Exit: PA 113 SOUTH - DOWNINGTOWN. Estimated Reopen: 4/10/26 - 07:39"
    },
    {
      "type": "Incident - Major Route",
      "roadway": "US - 422",
      "state": "Pennsylvania",
      "county": "Berks",
      "route": "US-422",
      "direction": "WEST",
      "description": "Disabled vehicle on US 422 westbound at Exit: N WYOMISSING BOULEVARD. There is a lane restriction.",
      "start_time": "4/10/26, 6:20 AM",
      "anticipated_end_time": "4/10/26, 9:45 AM",
      "last_updated": "4/10/26, 6:22 AM",
      "formatted": "US-422 (Berks County) | Disabled vehicle on US 422 westbound at Exit: N WYOMISSING BOULEVARD. Estimated Reopen: 4/10/26 - 09:45"
    }
  ]
}