{
  "name": "lane_restrictions",
  "fetched_at": "2026-04-02T05:56:46.418Z",
  "source_url": "https://www.511pa.com/list/events/traffic?start=0&length=250&order%5Bi%5D=8&order%5Bdir%5D=desc",
  "count": 4,
  "items": [
    {
      "type": "Incident - Major Route",
      "roadway": "I-81",
      "state": "Pennsylvania",
      "county": "Dauphin",
      "route": "I-81",
      "direction": "NORTH",
      "description": "Crash on I-81 northbound .5 miles south of Exit : REST AREA/WEIGH STATION. There is a lane restriction.",
      "start_time": "4/2/26, 1:38 AM",
      "anticipated_end_time": "4/2/26, 4:00 AM",
      "last_updated": "4/2/26, 1:41 AM",
      "formatted": "I-81 (Dauphin County) | Crash on I-81 northbound .5 miles south of Exit : REST AREA/WEIGH STATION. Estimated Reopen: 4/2/26 - 04:00"
    },
    {
      "type": "Incident - Major Route",
      "roadway": "I-76",
      "state": "Pennsylvania",
      "county": "Philadelphia",
      "route": "I-76",
      "direction": "EAST",
      "description": "Crash on I-76 eastbound between Exit 340B: US 1 NORTH - ROOSEVELT BOULEVARD and Exit 341: MONTGOMERY DR/WEST RIVER DRIVE. There is a lane restriction.",
      "start_time": "4/2/26, 1:25 AM",
      "anticipated_end_time": "4/2/26, 2:25 AM",
      "last_updated": "4/2/26, 1:27 AM",
      "formatted": "I-76 (Philadelphia County) | Crash on I-76 eastbound between Exit 340B: US 1 NORTH - ROOSEVELT BOULEVARD and Exit 341: MONTGOMERY DR/WEST RIVER DRIVE. Estimated Reopen: 4/2/26 - 02:25"
    },
    {
      "type": "Incident - Major Route",
      "roadway": "US-01",
      "state": "Pennsylvania",
      "county": "Philadelphia",
      "route": "US-01",
      "direction": "SOUTH",
      "description": "Crash on US 1 southbound between 1 miles NORTH of Exit: RIDGE AVE/KELLY DRIVE and Exit: I-76 WEST - VALLEY FORGE. There is a lane restriction.",
      "start_time": "4/1/26, 11:30 PM",
      "anticipated_end_time": "4/2/26, 2:30 AM",
      "last_updated": "4/2/26, 1:14 AM",
      "formatted": "US-01 (Philadelphia County) | Crash on US 1 southbound between 1 miles NORTH of Exit: RIDGE AVE/KELLY DRIVE and Exit: I-76 WEST - VALLEY FORGE. Estimated Reopen: 4/2/26 - 02:30"
    },
    {
      "type": "Incident - Major Route",
      "roadway": "I-95",
      "state": "Pennsylvania",
      "county": "Philadelphia",
      "route": "I-95",
      "direction": "SOUTH",
      "description": "Crash on I-95 southbound between Exit 32: ACADEMY ROAD/LINDEN AVE and Exit 30: COTTMAN AVE/RHAWN ST. There is a lane restriction.",
      "start_time": "4/1/26, 11:51 PM",
      "anticipated_end_time": "4/2/26, 2:50 AM",
      "last_updated": "4/2/26, 12:01 AM",
      "formatted": "I-95 (Philadelphia County) | Crash on I-95 southbound between Exit 32: ACADEMY ROAD/LINDEN AVE and Exit 30: COTTMAN AVE/RHAWN ST. Estimated Reopen: 4/2/26 - 02:50"
    }
  ]
}