{
  "name": "lane_restrictions",
  "fetched_at": "2026-05-16T13:58:22.196Z",
  "source_url": "https://www.511pa.com/list/events/traffic?start=0&length=250&order%5Bi%5D=8&order%5Bdir%5D=desc",
  "count": 1,
  "items": [
    {
      "id": "257085",
      "eventId": "257085",
      "type": "Incident - Major Route",
      "roadway": "I-76",
      "state": "Pennsylvania",
      "county": "Philadelphia",
      "route": "I-76",
      "direction": "EAST",
      "description": "Multi vehicle crash on I-76 eastbound between Exit 341: MONTGOMERY DR/WEST RIVER DRIVE and .4 miles east of Exit 342: US 13/30 WEST - GIRARD AVE/PHILA ZOO. There is a lane restriction.",
      "start_time": "5/16/26, 9:50 AM",
      "anticipated_end_time": "5/16/26, 10:55 AM",
      "last_updated": "5/16/26, 9:51 AM",
      "formatted": "I-76 (Philadelphia County) | Multi vehicle crash on I-76 eastbound between Exit 341: MONTGOMERY DR/WEST RIVER DRIVE and .4 miles east of Exit 342: US 13/30 WEST - GIRARD AVE/PHILA ZOO. Estimated Reopen: 5/16/26 - 10:55"
    }
  ]
}