{
  "name": "major_route_closures",
  "fetched_at": "2026-03-17T21:31:10.409Z",
  "source_url": "https://www.511pa.com/list/events/traffic?start=0&length=250&order%5Bi%5D=8&order%5Bdir%5D=desc",
  "count": 3,
  "items": [
    {
      "route": "US-422",
      "direction": "EAST",
      "between": null,
      "county": "Berks",
      "anticipated_end_time": "3/17/26, 7:45 PM",
      "description": "Police activity on US 422 eastbound between Exit: I-176 SOUTH - MORGANTOWN and Exit: MT PENN/SR 2039. All lanes closed.",
      "formatted": "US-422 (Berks County) | Police activity on US 422 eastbound between Exit: I-176 SOUTH - MORGANTOWN and Exit: MT PENN/SR 2039. All lanes Closed. Estimated Reopen: 3/17/26 - 19:45"
    },
    {
      "route": "US-222",
      "direction": "SOUTH",
      "between": null,
      "county": "Berks",
      "anticipated_end_time": "3/18/26, 11:30 AM",
      "description": "Downed tree in wires on US 222 southbound between MOSELEM SPRINGS RD and CALCIUM RDMAIN ST. All lanes closed.",
      "formatted": "US-222 (Berks County) | Downed tree in wires on US 222 southbound between MOSELEM SPRINGS RD and CALCIUM RDMAIN ST. All lanes Closed. Estimated Reopen: 3/18/26 - 11:30"
    },
    {
      "route": "US-222",
      "direction": "NORTH",
      "between": null,
      "county": "Berks",
      "anticipated_end_time": "3/18/26, 11:30 AM",
      "description": "Downed tree in wires on US 222 northbound between CALCIUM RDMAIN ST and MOSELEM SPRINGS RD. All lanes closed.",
      "formatted": "US-222 (Berks County) | Downed tree in wires on US 222 northbound between CALCIUM RDMAIN ST and MOSELEM SPRINGS RD. All lanes Closed. Estimated Reopen: 3/18/26 - 11:30"
    }
  ]
}