{
  "name": "ppl_power_outages_pa",
  "fetched_at": "2026-04-03T18:50:34Z",
  "source": "PPL",
  "total_customers_out": 156,
  "county_summary": [
    {
      "county": "Cumberland",
      "customers_out": 47,
      "customers_served": 108163,
      "percent_out": 0.04,
      "source": "PPL"
    },
    {
      "county": "Cumberland",
      "customers_out": 47,
      "customers_served": 108163,
      "percent_out": 0.04,
      "source": "PPL"
    },
    {
      "county": "Lehigh",
      "customers_out": 18,
      "customers_served": 180287,
      "percent_out": 0.01,
      "source": "PPL"
    },
    {
      "county": "Lehigh",
      "customers_out": 18,
      "customers_served": 180287,
      "percent_out": 0.01,
      "source": "PPL"
    },
    {
      "county": "Schuylkill",
      "customers_out": 8,
      "customers_served": 134024,
      "percent_out": 0.01,
      "source": "PPL"
    },
    {
      "county": "Schuylkill",
      "customers_out": 8,
      "customers_served": 134024,
      "percent_out": 0.01,
      "source": "PPL"
    },
    {
      "county": "Bucks",
      "customers_out": 2,
      "customers_served": 34267,
      "percent_out": 0.01,
      "source": "PPL"
    },
    {
      "county": "Lancaster",
      "customers_out": 2,
      "customers_served": 258148,
      "percent_out": 0.0,
      "source": "PPL"
    },
    {
      "county": "Bucks",
      "customers_out": 2,
      "customers_served": 34267,
      "percent_out": 0.01,
      "source": "PPL"
    },
    {
      "county": "Lancaster",
      "customers_out": 2,
      "customers_served": 258148,
      "percent_out": 0.0,
      "source": "PPL"
    },
    {
      "county": "Chester",
      "customers_out": 1,
      "customers_served": 13051,
      "percent_out": 0.01,
      "source": "PPL"
    },
    {
      "county": "Chester",
      "customers_out": 1,
      "customers_served": 13051,
      "percent_out": 0.01,
      "source": "PPL"
    }
  ],
  "items": [
    {
      "municipality": "Middlesex Twp",
      "county": "Cumberland",
      "customers_out": 47,
      "customers_served": 1315,
      "percent_out": 3.57,
      "source": "PPL"
    },
    {
      "municipality": "Middlesex Twp",
      "county": "Cumberland",
      "customers_out": 47,
      "customers_served": 1315,
      "percent_out": 3.57,
      "source": "PPL"
    },
    {
      "municipality": "Allentown",
      "county": "Lehigh",
      "customers_out": 18,
      "customers_served": 55848,
      "percent_out": 0.03,
      "source": "PPL"
    },
    {
      "municipality": "Allentown",
      "county": "Lehigh",
      "customers_out": 18,
      "customers_served": 55848,
      "percent_out": 0.03,
      "source": "PPL"
    },
    {
      "municipality": "Pine Grove Twp",
      "county": "Schuylkill",
      "customers_out": 8,
      "customers_served": 5041,
      "percent_out": 0.16,
      "source": "PPL"
    },
    {
      "municipality": "Pine Grove Twp",
      "county": "Schuylkill",
      "customers_out": 8,
      "customers_served": 5041,
      "percent_out": 0.16,
      "source": "PPL"
    },
    {
      "municipality": "Springfield Twp",
      "county": "Bucks",
      "customers_out": 2,
      "customers_served": 2033,
      "percent_out": 0.1,
      "source": "PPL"
    },
    {
      "municipality": "Manheim Twp",
      "county": "Lancaster",
      "customers_out": 2,
      "customers_served": 16882,
      "percent_out": 0.01,
      "source": "PPL"
    },
    {
      "municipality": "Springfield Twp",
      "county": "Bucks",
      "customers_out": 2,
      "customers_served": 2033,
      "percent_out": 0.1,
      "source": "PPL"
    },
    {
      "municipality": "Manheim Twp",
      "county": "Lancaster",
      "customers_out": 2,
      "customers_served": 16882,
      "percent_out": 0.01,
      "source": "PPL"
    },
    {
      "municipality": "Honeybrook Twp",
      "county": "Chester",
      "customers_out": 1,
      "customers_served": 6076,
      "percent_out": 0.02,
      "source": "PPL"
    },
    {
      "municipality": "Honeybrook Twp",
      "county": "Chester",
      "customers_out": 1,
      "customers_served": 6076,
      "percent_out": 0.02,
      "source": "PPL"
    }
  ]
}