{
  "fetched_at": "2026-04-28T15:35:23Z",
  "reason": "Successful PPL table capture",
  "click_result": {
    "clicked": true,
    "text": "View Outages By County"
  },
  "table_count": 2,
  "title": "PPL Outage Map",
  "row_count": 124,
  "row_preview": [
    [
      "County & Municipality",
      "Customers Affected",
      "Customers Served",
      "View On Map"
    ],
    [
      "Berks",
      "3",
      "48,966"
    ],
    [
      "Cumru Twp",
      "2",
      "619"
    ],
    [
      "Lower Heidelberg Twp",
      "1",
      "795"
    ],
    [
      "Bucks",
      "1",
      "34,267"
    ],
    [
      "Springfield Twp",
      "1",
      "2,033"
    ],
    [
      "Carbon",
      "7",
      "54,854"
    ],
    [
      "Lower Towamensing Twp",
      "3",
      "4,284"
    ],
    [
      "Penn Forest Twp",
      "4",
      "7,202"
    ],
    [
      "Chester",
      "13",
      "13,051"
    ],
    [
      "Honeybrook Twp",
      "13",
      "6,076"
    ],
    [
      "Columbia",
      "5",
      "63,819"
    ],
    [
      "Pine Twp",
      "3",
      "1,062"
    ],
    [
      "South Centre Twp",
      "2",
      "1,726"
    ],
    [
      "Cumberland",
      "3",
      "108,163"
    ],
    [
      "Lower Allen Twp",
      "3",
      "8,254"
    ],
    [
      "Dauphin",
      "1",
      "141,213"
    ],
    [
      "South Hanover Twp",
      "1",
      "2,444"
    ],
    [
      "Lackawanna",
      "45",
      "142,765"
    ],
    [
      "Carbondale",
      "21",
      "6,367"
    ]
  ]
}