{
  "name": "ppl_power_outages_pa",
  "fetched_at": "2026-04-09T09:23:44Z",
  "source": "PPL",
  "total_customers_out": 2,
  "county_summary": [
    {
      "county": "Columbia",
      "customers_out": 1,
      "customers_served": 63819,
      "percent_out": 0.0,
      "source": "PPL"
    },
    {
      "county": "Columbia",
      "customers_out": 1,
      "customers_served": 63819,
      "percent_out": 0.0,
      "source": "PPL"
    }
  ],
  "items": [
    {
      "municipality": "Scott Twp",
      "county": "Columbia",
      "customers_out": 1,
      "customers_served": 5220,
      "percent_out": 0.02,
      "source": "PPL"
    },
    {
      "municipality": "Scott Twp",
      "county": "Columbia",
      "customers_out": 1,
      "customers_served": 5220,
      "percent_out": 0.02,
      "source": "PPL"
    }
  ]
}