{
  "fetched_at": "2026-03-19T11:02:07Z",
  "reason": "Successful PPL table capture",
  "click_result": {
    "clicked": true,
    "text": "View Outages By County"
  },
  "table_count": 2,
  "title": "PPL Outage Map",
  "row_count": 14,
  "row_preview": [
    [
      "County & Municipality",
      "Customers Affected",
      "Customers Served",
      "View On Map"
    ],
    [
      "Lehigh",
      "13",
      "180,287"
    ],
    [
      "Allentown",
      "8",
      "55,848"
    ],
    [
      "North Whitehall Twp",
      "5",
      "5,212"
    ],
    [
      "Northampton",
      "3",
      "89,426"
    ],
    [
      "Bethlehem",
      "1",
      "22,034"
    ],
    [
      "Lower Saucon Twp",
      "2",
      "12,554"
    ],
    [
      "County & Municipality",
      "Customers Affected",
      "Customers Served",
      "View On Map"
    ],
    [
      "Lehigh",
      "13",
      "180,287"
    ],
    [
      "Allentown",
      "8",
      "55,848"
    ],
    [
      "North Whitehall Twp",
      "5",
      "5,212"
    ],
    [
      "Northampton",
      "3",
      "89,426"
    ],
    [
      "Bethlehem",
      "1",
      "22,034"
    ],
    [
      "Lower Saucon Twp",
      "2",
      "12,554"
    ]
  ]
}