{
  "name": "ppl_power_outages_pa",
  "fetched_at": "2026-03-22T12:54:09Z",
  "source": "PPL",
  "total_customers_out": 800,
  "county_summary": [
    {
      "county": "Monroe",
      "customers_out": 352,
      "customers_served": 74619,
      "percent_out": 0.47,
      "source": "PPL"
    },
    {
      "county": "Monroe",
      "customers_out": 352,
      "customers_served": 74619,
      "percent_out": 0.47,
      "source": "PPL"
    },
    {
      "county": "Snyder",
      "customers_out": 39,
      "customers_served": 30605,
      "percent_out": 0.13,
      "source": "PPL"
    },
    {
      "county": "Snyder",
      "customers_out": 39,
      "customers_served": 30605,
      "percent_out": 0.13,
      "source": "PPL"
    },
    {
      "county": "Pike",
      "customers_out": 3,
      "customers_served": 25461,
      "percent_out": 0.01,
      "source": "PPL"
    },
    {
      "county": "Pike",
      "customers_out": 3,
      "customers_served": 25461,
      "percent_out": 0.01,
      "source": "PPL"
    },
    {
      "county": "Berks",
      "customers_out": 2,
      "customers_served": 48966,
      "percent_out": 0.0,
      "source": "PPL"
    },
    {
      "county": "Clinton",
      "customers_out": 2,
      "customers_served": 26569,
      "percent_out": 0.01,
      "source": "PPL"
    },
    {
      "county": "Berks",
      "customers_out": 2,
      "customers_served": 48966,
      "percent_out": 0.0,
      "source": "PPL"
    },
    {
      "county": "Clinton",
      "customers_out": 2,
      "customers_served": 26569,
      "percent_out": 0.01,
      "source": "PPL"
    },
    {
      "county": "Cumberland",
      "customers_out": 1,
      "customers_served": 108163,
      "percent_out": 0.0,
      "source": "PPL"
    },
    {
      "county": "Juniata",
      "customers_out": 1,
      "customers_served": 24072,
      "percent_out": 0.0,
      "source": "PPL"
    },
    {
      "county": "Cumberland",
      "customers_out": 1,
      "customers_served": 108163,
      "percent_out": 0.0,
      "source": "PPL"
    },
    {
      "county": "Juniata",
      "customers_out": 1,
      "customers_served": 24072,
      "percent_out": 0.0,
      "source": "PPL"
    }
  ],
  "items": [
    {
      "municipality": "Barrett Twp",
      "county": "Monroe",
      "customers_out": 352,
      "customers_served": 3665,
      "percent_out": 9.6,
      "source": "PPL"
    },
    {
      "municipality": "Barrett Twp",
      "county": "Monroe",
      "customers_out": 352,
      "customers_served": 3665,
      "percent_out": 9.6,
      "source": "PPL"
    },
    {
      "municipality": "West Beaver Twp",
      "county": "Snyder",
      "customers_out": 39,
      "customers_served": 403,
      "percent_out": 9.68,
      "source": "PPL"
    },
    {
      "municipality": "West Beaver Twp",
      "county": "Snyder",
      "customers_out": 39,
      "customers_served": 403,
      "percent_out": 9.68,
      "source": "PPL"
    },
    {
      "municipality": "Lackawaxen Twp",
      "county": "Pike",
      "customers_out": 3,
      "customers_served": 6051,
      "percent_out": 0.05,
      "source": "PPL"
    },
    {
      "municipality": "Lackawaxen Twp",
      "county": "Pike",
      "customers_out": 3,
      "customers_served": 6051,
      "percent_out": 0.05,
      "source": "PPL"
    },
    {
      "municipality": "Spring Twp",
      "county": "Berks",
      "customers_out": 2,
      "customers_served": 8308,
      "percent_out": 0.02,
      "source": "PPL"
    },
    {
      "municipality": "Bald Eagle Twp",
      "county": "Clinton",
      "customers_out": 2,
      "customers_served": 912,
      "percent_out": 0.22,
      "source": "PPL"
    },
    {
      "municipality": "Spring Twp",
      "county": "Berks",
      "customers_out": 2,
      "customers_served": 8308,
      "percent_out": 0.02,
      "source": "PPL"
    },
    {
      "municipality": "Bald Eagle Twp",
      "county": "Clinton",
      "customers_out": 2,
      "customers_served": 912,
      "percent_out": 0.22,
      "source": "PPL"
    },
    {
      "municipality": "North Middleton Twp",
      "county": "Cumberland",
      "customers_out": 1,
      "customers_served": 7776,
      "percent_out": 0.01,
      "source": "PPL"
    },
    {
      "municipality": "Walker Twp",
      "county": "Juniata",
      "customers_out": 1,
      "customers_served": 5936,
      "percent_out": 0.02,
      "source": "PPL"
    },
    {
      "municipality": "North Middleton Twp",
      "county": "Cumberland",
      "customers_out": 1,
      "customers_served": 7776,
      "percent_out": 0.01,
      "source": "PPL"
    },
    {
      "municipality": "Walker Twp",
      "county": "Juniata",
      "customers_out": 1,
      "customers_served": 5936,
      "percent_out": 0.02,
      "source": "PPL"
    }
  ]
}