{
  "name": "ppl_power_outages_pa",
  "fetched_at": "2026-05-07T12:07:16Z",
  "source": "PPL",
  "total_customers_out": 212,
  "county_summary": [
    {
      "county": "Lancaster",
      "customers_out": 37,
      "customers_served": 258148,
      "percent_out": 0.01,
      "source": "PPL"
    },
    {
      "county": "Lancaster",
      "customers_out": 37,
      "customers_served": 258148,
      "percent_out": 0.01,
      "source": "PPL"
    },
    {
      "county": "Lancaster",
      "customers_out": 36,
      "customers_served": 24682,
      "percent_out": 0.15,
      "source": "PPL"
    },
    {
      "county": "Lancaster",
      "customers_out": 36,
      "customers_served": 24682,
      "percent_out": 0.15,
      "source": "PPL"
    },
    {
      "county": "Cumberland",
      "customers_out": 12,
      "customers_served": 108163,
      "percent_out": 0.01,
      "source": "PPL"
    },
    {
      "county": "Cumberland",
      "customers_out": 12,
      "customers_served": 108163,
      "percent_out": 0.01,
      "source": "PPL"
    },
    {
      "county": "Luzerne",
      "customers_out": 7,
      "customers_served": 150605,
      "percent_out": 0.0,
      "source": "PPL"
    },
    {
      "county": "Luzerne",
      "customers_out": 7,
      "customers_served": 150605,
      "percent_out": 0.0,
      "source": "PPL"
    },
    {
      "county": "Wilkes-Barre",
      "customers_out": 6,
      "customers_served": 15951,
      "percent_out": 0.04,
      "source": "PPL"
    },
    {
      "county": "Wilkes-Barre",
      "customers_out": 6,
      "customers_served": 15951,
      "percent_out": 0.04,
      "source": "PPL"
    },
    {
      "county": "Monroe",
      "customers_out": 4,
      "customers_served": 74619,
      "percent_out": 0.01,
      "source": "PPL"
    },
    {
      "county": "Monroe",
      "customers_out": 4,
      "customers_served": 74619,
      "percent_out": 0.01,
      "source": "PPL"
    },
    {
      "county": "Bucks",
      "customers_out": 2,
      "customers_served": 34267,
      "percent_out": 0.01,
      "source": "PPL"
    },
    {
      "county": "Dauphin",
      "customers_out": 2,
      "customers_served": 141213,
      "percent_out": 0.0,
      "source": "PPL"
    },
    {
      "county": "Bucks",
      "customers_out": 2,
      "customers_served": 34267,
      "percent_out": 0.01,
      "source": "PPL"
    },
    {
      "county": "Dauphin",
      "customers_out": 2,
      "customers_served": 141213,
      "percent_out": 0.0,
      "source": "PPL"
    }
  ],
  "items": [
    {
      "municipality": "North Newton Twp",
      "county": "Cumberland",
      "customers_out": 12,
      "customers_served": 363,
      "percent_out": 3.31,
      "source": "PPL"
    },
    {
      "municipality": "North Newton Twp",
      "county": "Cumberland",
      "customers_out": 12,
      "customers_served": 363,
      "percent_out": 3.31,
      "source": "PPL"
    },
    {
      "municipality": "Tobyhanna Twp",
      "county": "Monroe",
      "customers_out": 4,
      "customers_served": 11835,
      "percent_out": 0.03,
      "source": "PPL"
    },
    {
      "municipality": "Tobyhanna Twp",
      "county": "Monroe",
      "customers_out": 4,
      "customers_served": 11835,
      "percent_out": 0.03,
      "source": "PPL"
    },
    {
      "municipality": "Springfield Twp",
      "county": "Bucks",
      "customers_out": 2,
      "customers_served": 2033,
      "percent_out": 0.1,
      "source": "PPL"
    },
    {
      "municipality": "Middle Paxton Twp",
      "county": "Dauphin",
      "customers_out": 2,
      "customers_served": 2683,
      "percent_out": 0.07,
      "source": "PPL"
    },
    {
      "municipality": "Springfield Twp",
      "county": "Bucks",
      "customers_out": 2,
      "customers_served": 2033,
      "percent_out": 0.1,
      "source": "PPL"
    },
    {
      "municipality": "Middle Paxton Twp",
      "county": "Dauphin",
      "customers_out": 2,
      "customers_served": 2683,
      "percent_out": 0.07,
      "source": "PPL"
    },
    {
      "municipality": "East Donegal Twp",
      "county": "Lancaster",
      "customers_out": 1,
      "customers_served": 7378,
      "percent_out": 0.01,
      "source": "PPL"
    },
    {
      "municipality": "Butler Twp",
      "county": "Luzerne",
      "customers_out": 1,
      "customers_served": 4395,
      "percent_out": 0.02,
      "source": "PPL"
    },
    {
      "municipality": "East Donegal Twp",
      "county": "Lancaster",
      "customers_out": 1,
      "customers_served": 7378,
      "percent_out": 0.01,
      "source": "PPL"
    },
    {
      "municipality": "Butler Twp",
      "county": "Luzerne",
      "customers_out": 1,
      "customers_served": 4395,
      "percent_out": 0.02,
      "source": "PPL"
    }
  ]
}