{
  "fetched_at": "2026-04-05T20:54:00Z",
  "reason": "Successful PPL table capture",
  "click_result": {
    "clicked": true,
    "text": "View Outages By County"
  },
  "table_count": 2,
  "title": "PPL Outage Map",
  "row_count": 34,
  "row_preview": [
    [
      "County & Municipality",
      "Customers Affected",
      "Customers Served",
      "View On Map"
    ],
    [
      "Carbon",
      "2",
      "54,854"
    ],
    [
      "Franklin Twp",
      "2",
      "6,815"
    ],
    [
      "Columbia",
      "3",
      "63,819"
    ],
    [
      "Beaver Twp",
      "3",
      "473"
    ],
    [
      "Lackawanna",
      "221",
      "142,764"
    ],
    [
      "Roaring Brook Twp",
      "27",
      "1,790"
    ],
    [
      "Throop Boro",
      "194",
      "5,149"
    ],
    [
      "Lancaster",
      "596",
      "258,148"
    ],
    [
      "Mount Joy Twp",
      "595",
      "5,566"
    ],
    [
      "West Donegal Twp",
      "1",
      "958"
    ],
    [
      "Northumberland",
      "12",
      "84,555"
    ],
    [
      "Little Mahanoy Twp",
      "12",
      "2,401"
    ],
    [
      "Perry",
      "24",
      "43,924"
    ],
    [
      "Saville Twp",
      "24",
      "1,494"
    ],
    [
      "Wayne",
      "233",
      "51,383"
    ],
    [
      "Berlin Twp",
      "233",
      "3,568"
    ],
    [
      "County & Municipality",
      "Customers Affected",
      "Customers Served",
      "View On Map"
    ],
    [
      "Carbon",
      "2",
      "54,854"
    ],
    [
      "Franklin Twp",
      "2",
      "6,815"
    ]
  ]
}