{
  "fetched_at": "2026-04-13T18:42:21Z",
  "reason": "Successful PPL table capture",
  "click_result": {
    "clicked": true,
    "text": "View Outages By County"
  },
  "table_count": 2,
  "title": "PPL Outage Map",
  "row_count": 78,
  "row_preview": [
    [
      "County & Municipality",
      "Customers Affected",
      "Customers Served",
      "View On Map"
    ],
    [
      "Berks",
      "10",
      "48,966"
    ],
    [
      "Sinking Spring Boro",
      "10",
      "7,006"
    ],
    [
      "Columbia",
      "9",
      "63,819"
    ],
    [
      "Bloomsburg",
      "8",
      "9,976"
    ],
    [
      "Orange Twp",
      "1",
      "897"
    ],
    [
      "Cumberland",
      "1",
      "108,163"
    ],
    [
      "North Middleton Twp",
      "1",
      "7,776"
    ],
    [
      "Juniata",
      "11",
      "24,072"
    ],
    [
      "Milford Twp",
      "11",
      "1,123"
    ],
    [
      "Lackawanna",
      "3",
      "142,764"
    ],
    [
      "Scott Twp",
      "3",
      "3,598"
    ],
    [
      "Lancaster",
      "5",
      "258,148"
    ],
    [
      "East Hempfield Twp",
      "5",
      "9,598"
    ],
    [
      "Lehigh",
      "12",
      "180,287"
    ],
    [
      "South Whitehall Twp",
      "4",
      "15,604"
    ],
    [
      "Whitehall Twp",
      "8",
      "9,147"
    ],
    [
      "Luzerne",
      "2",
      "150,605"
    ],
    [
      "Hazle Twp",
      "1",
      "17,783"
    ],
    [
      "Wilkes-Barre",
      "1",
      "15,951"
    ]
  ]
}